Metadata-Version: 2.4
Name: mseep-mcp-adb
Version: 0.1.1
Summary: An MCP server for Android automation using UIAutomator2
Author-email: mseep <support@skydeck.ai>
Requires-Python: >=3.13
License-File: LICENSE
Requires-Dist: asyncio>=3.4.3
Requires-Dist: mcp[cli]>=1.7.0
Requires-Dist: uiautodev>=0.6.0
Requires-Dist: uiautomator2>=3.2.9
Requires-Dist: python-multipart>=0.0.9
Requires-Dist: ruff>=0.11.8
Requires-Dist: pytest>=8.3.5
Requires-Dist: pytest-cov>=6.1.1
Requires-Dist: pytest-asyncio>=0.26.0
Dynamic: license-file
